{
  "imdbId" : "0000011",
  "title" : "The Road to Berlin",
  "releaseYear" : "2002",
  "duration" : "2:45",
  "rating" : "NOT RATED",
  "director" : "",
  "imageUrl" : "0000011.jpg",
  "description" : "The Eastern Front witnessed fighting and suffering on a scale almost inconceivable in the west. This was the most brutal theater of WWII. It claimed 28 million lives and redrew the maps of Europe for over a half century. Based on previously classified Soviet military footage.",
  "genres" : [ "Documentary", "History" ],
  "cast" : [ ],
  "tags" : [ "WW-II" ]
}
