{
  "imdbId" : "0072308",
  "title" : "The Towering Inferno",
  "releaseYear" : "1974",
  "duration" : "2:45",
  "rating" : "PG",
  "director" : "John Guillermin",
  "imageUrl" : "0072308.jpg",
  "description" : "At the opening party of a colossal, but poorly constructed, office building, a massive fire breaks out that threatens to destroy the tower and everyone in it.",
  "genres" : [ "Action", "Drama", "Thriller" ],
  "cast" : [ "Steve McQueen", "Paul Newman", "William Holden", "Faye Dunaway", "Fred Astaire", "Susan Blakely", "Richard Chamberlain", "Jennifer Jones", "O.J. Simpson", "Robert Vaughn", "Robert Wagner", "Susan Flannery", "Sheila Allen", "Norman Burton", "Jack Collins", "Don Gordon", "Felton Perry", "Gregory Sierra", "Ernie F. Orsatti", "Dabney Coleman", "Elizabeth Rogers", "Ann Leicester", "Norman Grabowski", "Ross Elliott", "Olan Soule", "Carlena Gower", "Mike Lookinland", "Carol McEvoy", "Scott Newman", "Paul Comi", "George D. Wallace", "Patrick Culliton", "William Bassett", "John Crawford", "Erik L. Nelson", "Art Balinger", "Norman Hicks", "Thomas Karnahan", "Beau Anderson", "Shirley Anthony", "David Armstrong", "Larry Arnold", "Malcolm Atterbury", "Buzz Barbee", "Al Beaudine", "Don Bledsoe", "John Blower", "Robert Buckingham", "Dusty Cadis", "Larry Carr", "Marcello Clay", "Ken Clayton", "Robert Cole", "Joe DeAngelo", "Paula Dell", "James Dukas", "Ken DuMain", "Brent Dunsford", "Peter Eastman", "Patty Elder", "Gwen Farrell", "Ruth Foster", "Michael J. Grayson", "Raven Grey Eagle", "Ralph Grosh", "Valerie Hall", "Orwin C. Harvey", "Francine Henderson", "Harry Hickox", "Robert Hitchcock", "Chris Holter", "Kathryn Janssen", "Dale Johnson", "Mike Johnson", "Paul King", "Jack Krupnick", "Tom Lawrence", "Ethelreda Leopold", "Bob Liddle", "John Marlin", "Steven Marlo", "Maureen McGovern", "John Hugh McKnight", "Clyde McLeod", "John Moio", "Tony Piazza", "Jennifer Rhodes", "Leoda Richards", "Hank Robinson", "Glynn Rubin", "Shelley Snell", "Norman Stevans", "Nico Stevens", "Robert Strong", "Jenny Sullivan", "Carlos Tappin", "Don Terwilliger", "Elizabeth Thompson", "Victor Toyota", "William Traylor", "John Vick", "Tim Wallace", "Gary Wright", "Dee Dee Young" ],
  "tags" : [ ]
}