{
  "imdbId" : "0088571",
  "title" : "Moonlighting",
  "releaseYear" : "1985",
  "duration" : "1:00",
  "rating" : "NOT RATED",
  "director" : "",
  "imageUrl" : "0088571.jpg",
  "description" : "The quirky cases of a former model and a smart aleck detective who manage a private detective agency.",
  "genres" : [ "Comedy", "Drama", "Mystery" ],
  "cast" : [ "Cybill Shepherd", "Bruce Willis", "Allyce Beasley", "Curtis Armstrong", "Jack Blessing", "Jonathan Ames", "Kristine Kauffman", "Daniel Fitzpatrick", "Robert Webber", "Charles Rocket", "Jamie Taylor", "Eva Marie Saint", "Clinton Allmon", "Mark Harmon", "Dennis Dugan", "Willie Brown", "Virginia Madsen", "Brooke Adams", "Bill Marcus", "Caitlin Clarke", "Gary Cole", "Ronald G. Joseph", "Tracey Walter", "Tony Bill", "Julia Jennings", "R.H. Thomson", "Howard Mann", "Will Nye", "Henry G. Sanders", "Frantz Turner", "Pamela Bowen", "Allan Kolman", "Kate Murtagh", "Michael E. Dawdy", "Jensen Collier", "Cleavant Derricks", "Leigh Webb", "Rob Wickstrom", "Rocky Giordani", "Zack Phifer", "Jack Murdock", "Tammy Brewer", "Chris Rennolds", "Darwyn Swalve", "Fred Ottaviano", "Dana Delany", "Judith Hansen", "Dan Lauria", "Gregg Henry", "Vincent Schiavelli", "Donna Dixon", "Dennis Christopher", "Whoopi Goldberg", "Richard Kuhlman", "Robert Wuhl", "Inez Edwards", "Christine Haber", "Lyle Howry", "Barbara Bain", "Jack Bannon", "Richard Belzer", "Jon Cedar", "George Coe", "Pat Corley", "Robert Ellenstein", "Alexandra Johnson", "Mark Lonow", "Cotter Smith", "Lisa Blount", "Brad Dourif", "Ellen Geer", "Stephen Godwin", "Jim Haynie", "Nora Heflin", "Marilyn Jones", "Richard Libertini", "Will MacMillan", "Kenneth McMillan", "Judd Nelson", "J.A. Preston", "Paul Roebling", "Paul Sorvino", "Granville Van Dusen", "Rona Barrett", "Rhoda Gemignani", "Ann Hearn", "Alan Blumenfeld", "John Calvin", "Joel Colodner", "Sid Conrad", "Rick Jason", "Robert Joy", "Lenore Kasdorf", "David Patrick Kelly", "Jim McKrell", "Joel Polis", "Tim Robbins", "Phil Rubenstein", "Jonathan Stark", "Barbara Stock", "Arthur Taxier", "Leslie Wing", "Andra Akers", "Brooke Bundy", "K Callan", "Ralph Drischell", "Teri Hafford", "Jessica Harper", "Rosanna Huffman", "Steven Keats", "Michael MacRae", "Alley Mills", "David Paymer", "Marshall R. Teague", "Brynn Thayer", "Linda Thorson", "Deborah Wakeham", "John Lehne", "Andrew Masset", "Scott Paulin", "William Washington", "Nicholas Cascone", "Karen Landry", "Joseph Maher", "Ben Piazza", "Cristine Rose", "Reni Santoni", "Jayne Atkinson", "Val Avery", "Colleen Dewhurst", "Michael Flynn", "Andrew Robinson", "Tim Thomerson", "Rita Wilson", "James Avery", "Raleigh Bond", "Tony Burton", "Danny Dayton", "Billy Drago", "Rick Fitts", "Michael Halsey", "James Karen", "Mark Linn-Baker", "Richard McGonagle", "Bill Morey", "Ed O'Ross", "Paul Rudd", "Ben Slack", "James Sloyan", "Leslie Ackerman", "Lieux Dressler", "Patricia Duff", "Martin Ferrero", "Steve James", "Edie McClurg", "Betty McGuire", "Joseph G. Medalis", "F.J. O'Neil", "F. William Parker", "Maurice Sneed", "Charlie Stavola", "Cheryl Tiegs", "David Wells", "Ray Charles", "Jack Goode Jr.", "William Hickey", "Karen Kondazian", "Sam McMurray", "Ana Alicia", "Gerald Anthony", "Graham Beckel", "Johnny Brown", "Imogene Coca", "Cristina Raines", "Lee Bryant", "Stephanie Dunnam", "Joseph Hacker", "Jon Korkes", "Eddie Mekka", "Lawrence Pressman", "Joan Pringle", "Nicholas Pryor", "James Stephens", "Ron Vernan", "Gary Carlos Cervantes", "Daniel Chodos", "Nora Gaye", "Anthony Gordon", "Gary Graham", "Joe Lambie", "Francis X. McCarthy", "Lisa Blake Richards", "Gene Ross", "Rebecca Stanley", "Dianne Travis", "James Walsh", "Sam Whipple", "Terry Wills", "Paul Willson", "Richard Beymer", "Roberts Blossom", "Jeffrey DeMunn", "Rick Ducommun", "Edith Fields", "Gerry Gibson", "John Kassir", "Sydney Lassick", "Hap Lawrence", "Tom McFadden", "Eddie Quillan", "Wally Taylor", "Richard Tyson", "Joyce Brothers", "H. Richard Greene", "Kay Lenz", "Terry O'Quinn", "Jeff Osterhage", "Ellen Albertini Dow", "Pat Boone", "Bruce French", "Stan Ivar", "Katie Layman", "Sagan Lewis", "Janet MacLachlan", "Rod McCary", "Alan McRae", "Bill Erwin", "Joe Grifasi", "Jane Hallaren", "Michelle Johnson", "Ford Rainey", "Beverly Sanders", "Phillip Simms", "Lora Staley", "Debra Stipe", "Ray Wise", "Nick Angotti", "Beau Billingslea", "Robert Alan Browne", "Leonard Frey", "J.D. Hall", "John Harkins", "John Hostetter", "Irwin Keyes", "Freeman King", "Dennis Lipscomb", "Kim North", "Joan Ryan", "Robert Z'Dar", "David Ankrum", "Allan Arkush", "Dominic Barto", "Guy Boyd", "Patti Cohoon-Friedman", "Dante D'Andre", "Jan B. Daly", "Michael Laskin", "Colm Meaney", "Mike Narz", "Stan Ross", "Judith Searle", "Douglas Warhit", "Ian Abercrombie", "Jane Daly", "John Goodman", "John McCook", "Dick Miller", "Walter Olkewicz", "Harold Surratt", "Al White", "John C. Anders", "Mark Arnott", "Mimi Cozzens", "Geoffrey Lardner", "Nancy Parsons", "Drew Pillsbury", "Eric Sinclair", "Ron Troncatty", "Jeff Allin", "Monty Bane", "Stephen Burleigh", "Gloria Cromwell", "Patti Deutsch", "Jay R. Goldenberg", "John C. Moskoff", "David Ruprecht", "Barbara Tarbuck", "Mark L. Taylor", "Vivian Bonnell", "Frederick Coffin", "Jim Doughan", "Ross Evans", "Tony Giorgio", "Bill Handy", "Russell Hines", "Mindi Iden", "Ralph Meyering Jr.", "Robert Moberly", "John Sinclair", "Garnett Smith", "James A. Williams", "Sandahl Bergman", "John Bower", "William Martin Burns", "Corinne Carroll", "Barry Cutler", "Bob Goldstein", "Duncan McLeod", "Santos Morales", "Eduardo Ricard", "Mario Roccuzzo", "Robina Suwol", "Charles Walker", "Chino 'Fats' Williams", "Abraham Alvarez", "Leo Gordon", "Tom Lacy", "Frances E. Nealy", "Tom O'Brien", "Stephanie Shroyer", "Biff Wiff", "Sandra Bogan", "James F. Dean", "Don Draper", "Gary Epper", "Ivy Jones", "Teresa Willis", "Tony Abatemarco", "Granville Ames", "Richard G. Camphuis", "John Capodice", "Ron Howard George", "Dan Gilvezan", "James Staley", "Jennifer Tilly", "George Wallace", "Patrick Alan", "Anthony Alexander", "Patricia Allison", "Billy Beck", "Nick DeMauro", "Richard Epcar", "Tyra Ferrell", "Mary Hart", "Jeffrey Lampert", "Brian Libby", "Paul Reid Roman", "Suzy Brabeau", "Joe Carafello", "John Gallogly", "Sterling Holloway", "Hettie Lynne Hurtes", "Allan Katz", "Patty Lotz", "Read Morgan", "Eve Smith", "David Clover", "Steve Eastin", "Charles Parks", "Amanda Plummer", "Shelly Desai", "Raymond Forchion", "Gonzalez Gonzalez", "Gene Hartline", "Paul Marin", "Melanie Vincz", "Mark Voland", "Patricia Lee Willson", "Terry Beaver", "Francis Coady", "Stanley DeSantis", "Jay Ingram", "Paul Mendoza", "Brian Routh", "Chris Callan", "Freddie Dawson", "Will Gill Jr.", "Wyatt Johnson", "Adriano Rebora", "Charles Seixas", "Orson Welles", "Bill Applegate", "Monty Ash", "Xander Berkeley", "P. Randall Bowers", "John Durbin", "David Ellzey", "Daniel Frishman", "Joe Howard", "Constance Pfeifer", "Alain Saint-Alix", "Lionel Stander", "Maggie Egan", "Penny Santon", "Romy Windsor", "Carmine Iannaccone", "Dave Nicolson", "Jason Ross", "Robin Welch", "Victor Bevine", "Shannon Farnon", "Leonard R. Garner Jr.", "Thomas Murphy", "Martin von Haselberg", "Melissa Weber", "Doug Dupuy", "Art K. Koustik", "Liz Sheridan", "Francisco Paco Vela", "Lucy Lee Flippin", "Radu Gavor", "Sid Kane", "Frank Miller", "Danny Stone", "Bunny Summers", "Peter Trencher", "David Q. Combs", "Anthony De Longis", "Harry Morgan Moses", "Tom Ashworth", "Marcelo Tubert", "Gwen Van Dam", "Chris Weatherhead", "Julie Bennett", "Marcia Ann Burrs", "Jerry Hauck", "Samantha Knight", "Charles Lanyer", "Timothy Leary", "Ed White", "Stan Barnett", "France Mayotte", "Raymond O'Keefe", "Dennis Stewart", "Sue Bugden", "Marc Christopher", "Frank Collison", "Patty Dworkin", "Ben Hartigan", "Don King", "Lawrence Trimble", "Cheryl Carter", "Beverly Hart", "Tony Pierce", "Nicholas Worth", "Harold Cannon", "Yvonne Farrow", "Anna Garduno", "Katherine Huston", "Katherine James", "Fred E. Baker", "Fritz Bronner", "Candy Darling", "Susan French", "Phillip Persons", "Jeff Rochlin", "Michael Speero", "Bill Saito", "Angelica Torres", "Joseph Whipp", "Richard Balin", "J.P. Bumstead", "Julie Hayek", "Jon Menick", "Julius Carry", "Lisa Mende", "Jacalyn O'Shaughnessy", "Ted Rogers", "Wendee Winters", "John David Conti", "Jonathan Hole", "Dore Keller", "David Kristin", "Frank Noon", "Randy Olea", "Andrew Reilly", "Jean Adams", "Lomax Study", "Ernie Lee Banks", "Suzanne Dunn", "Lorrie Marlow", "Mik One", "April Dawn", "Steve Nevil", "Jack Boyle", "Fritzi Burr", "Robert Kim", "Raf Nazario", "Bill Phillips", "Cary-Hiroyuki Tagawa", "Martin Charles Warner", "Rachel Bard", "Rio Fukuda", "E. Hampton Beagle", "Michael Francis Clarke", "Carole Tru Foster", "Raymond Guth", "Kristen Jensen", "Ken Foree", "Ken Phillips", "Stan Yale", "Cletus Young", "Charlie Holliday", "Kenneth J. Martinez", "Kendall McCarthy", "Paunita Nichols", "Lisa Stahl", "Blake Clark", "Lou Fillipo", "Marianne Muellerleile", "Jody Lee Olhava", "Jean Speegle Howard", "William Jones", "Howard Goodwin", "Steve Jones", "Stuart Nelson", "Suzanne Fagan", "Scanlon Gail", "Danna Hansen", "Mae Marmy", "David McKnight", "Buddy Powell", "John Lafayette", "Don Maxwell", "Sam Hennings", "Betty Bunch", "William Hubbard Knight", "Darrah Meeley", "Roderick Vann", "Nick Chavez", "Eddie Hailey", "Victoria Perry", "Joan McMurtrey", "Ray O'Conner", "Eric Poppick", "Jade Roberts", "Michelle Reese", "Anne Bellamy", "Ira S. Rosenstein", "Kelly Hine", "Tim Ryan", "Ron Porterfield", "Tom Reese", "John Medici", "James F. Kelly", "Raymond Ma", "Frank Pangborn", "Richmond Harrison", "Brian Thompson", "Eric Love", "Terri Lynn", "Matt McKenzie", "Dwight Wheaton-Werle", "Tricia Tomicic", "Bren McKinley", "Toni Sawyer", "Ron Colby", "Michel Voletti", "April Wayne", "Wren T. Brown", "Joe Costanza", "Bob Tzudiker", "Etan Boritzer", "Debra Christofferson", "Joey D. Vieira", "Larry Stewart", "R.J. Arterburn", "Pat Crawford Brown", "Steven Brian Smith", "Joel Simon", "John Paul Gamoke", "Connie Fredericks", "Howard Schechter", "Michael Novak", "Joseph Romeo", "Jerry Doyle", "Frank Rosch", "The Temptations", "Diana Lee Inosanto", "C. Thomas Howell", "Cynthia Windham", "Billy Barty", "Christopher Callen", "Cynthia Lea Clark", "Richard Dawson", "Carmen Filpi", "Colin Clive", "Melvin Franklin", "Valerie Hobson", "Boris Karloff", "Elsa Lanchester", "Beau Starr", "Ernest Thesiger", "Ron Tyson", "Bruce Van Patten", "Ruth Westheimer", "Otis Williams", "Ali Woodson", "Peter Bogdanovich", "Pierce Brosnan", "Randall 'Tex' Cobb", "Henry Fonda", "Cary Grant", "Katharine Hepburn", "Jeff Jarvis", "Myrna Loy", "Shawn McBurney", "William Powell", "The Raelettes", "Joseph Michael Roth", "Barbara Stanwyck", "John Agar", "The Beatles", "Terri Lynn Doss", "Oliver Hardy", "Adolf Hitler", "Curly Howard", "John Kennedy Jr.", "Stan Laurel", "Benito Mussolini", "Lee Harvey Oswald", "Bobbi Pavis", "Richard Simmons", "Shirley Temple", "Smith Wordes", "Jak Castro", "Demi Moore", "Rowan Grey Sutherland", "Grace Zabriskie" ],
  "tags" : [ "TV" ]
}
