{
  "imdbId" : "0169547",
  "title" : "American Beauty",
  "releaseYear" : "1999",
  "duration" : "2:02",
  "rating" : "R",
  "director" : "Sam Mendes",
  "imageUrl" : "0169547.jpg",
  "description" : "Lester Burnham, a depressed suburban father in a mid-life crisis, decides to turn his hectic life around after developing an infatuation for his daughter's attractive friend.",
  "genres" : [ "Drama" ],
  "cast" : [ "Kevin Spacey", "Annette Bening", "Thora Birch", "Wes Bentley", "Mena Suvari", "Chris Cooper", "Peter Gallagher", "Allison Janney", "Scott Bakula", "Sam Robards", "Barry Del Sherman", "Ara Celi", "John Cho", "Fort Atkinson", "Sue Casey", "Kent Faulcon", "Brenda Wehle", "Lisa Cloud", "Alison Faulk", "Krista Goodsitt", "Lily Houtkin", "Carolina Lancaster", "Mona Leah", "Chekesha Van Putten", "Emily Zachary", "Nancy Anderson", "Reshma Gajjar", "Stephanie Rizzo", "Heather Joy Sher", "Chelsea Hertford", "Amber Smith", "Joel McCrary", "Marissa Jaret Winokur", "Dennis Anderson", "Matthew Kimbrough", "Erin Cathryn Strubbe", "Bruce Cohen", "Elaine Corral Kendall", "David C. Fisher", "Tom Miller" ],
  "tags" : [ ]
}