{
  "imdbId" : "0401729",
  "title" : "John Carter",
  "releaseYear" : "2012",
  "duration" : "2:12",
  "rating" : "PG-13",
  "director" : "Andrew Stanton",
  "imageUrl" : "0401729.jpg",
  "description" : "Transported to Barsoom, a Civil War vet discovers a barren planet seemingly inhabited by 12-foot tall barbarians. Finding himself prisoner of these creatures, he escapes, only to encounter Woola and a princess in desperate need of a savior.",
  "genres" : [ "Action", "Adventure", "Fantasy" ],
  "cast" : [ "Taylor Kitsch", "Lynn Collins", "Samantha Morton", "Willem Dafoe", "Thomas Haden Church", "Mark Strong", "Ciarán Hinds", "Dominic West", "James Purefoy", "Bryan Cranston", "Polly Walker", "Daryl Sabara", "Arkie Reece", "Davood Ghadami", "Pippa Nixon", "James Embree", "Philip Philmar", "Figs Jackman", "Emily Tierney", "Edmund Kente", "Rupert Frazer", "Nicholas Woodeson", "Kyle Agnew", "Don Stark", "Josh Daugherty", "Jared Cyr", "Sean Carrigan", "Dusty Sorg", "Christopher Goodman", "Amanda Clayton", "Akima", "Joseph Billingiere", "Aldred Montoya", "Phil Cheadle", "David Schwimmer", "Arnie Alpert", "Ian Ray", "Peggy Clements", "Evelyn Dubuc", "Jhil McEntyre", "Daniel O'Meara", "Emma Clifford", "Oliver Boot", "Rebecca Sarker", "Philip Arditti", "Jon Favreau", "Art Malik", "Holly Weston", "Gary Milner", "Cate Fowler", "Darwin Shaw", "Eileen Page", "Simon Evans", "Myriam Acharki", "Steven Cree", "Garry Tubbs", "Jeremy Booth", "Jill Baker", "Devin Chase Allen", "Ekaterina Botziou", "Shane B. Cook", "Matt Lasky", "Morgan Lester", "Thomas J. Post", "Jacqui Shaw" ],
  "tags" : [ ]
}
