{
  "imdbId" : "1146438",
  "title" : "The Librarian: The Curse of the Judas Chalice",
  "releaseYear" : "2008",
  "duration" : "1:30",
  "rating" : "TV-PG",
  "director" : "Jonathan Frakes",
  "imageUrl" : "1146438.jpg",
  "description" : "After retrieving the philosopher's stone at an auction but losing his girlfriend, The Librarian Flynn Carsen has a breakdown. Charlene and Judson ask him to spend some time on vacation.",
  "genres" : [ "Action", "Adventure", "Comedy", "Fantasy", "Romance", "Thriller" ],
  "cast" : [ "Noah Wyle", "Bruce Davison", "Stana Katic", "Bob Newhart", "Jane Curtin", "Dikran Tulaine", "Jason Douglas", "Beth Burvant", "Joe Knezevich", "David Born", "Joe Ross", "John Curran", "Connor Hill", "Aimée Spring Fortier", "Todd Voltz", "Werner Richmond", "Armando Leduc", "Sean Elliot", "David Calhoun", "John Wilmot", "Brandi Gerard", "Earl Maddox", "Ernie Williams", "Ted Alderman", "Monica Rene'e Anderson", "Natasha ", "Albert H. Bongard IV", "Allen Boudreaux", "John Ceallach", "Stanley Chauvin", "Antonio Echeverria", "Jonathan Frakes", "Frazier Hicks", "Victor E. Hugo", "Cynthia LeBlanc", "Elton LeBlanc", "Jessica Luebe", "Joseph Meissner", "Ritchie Montgomery", "Jay Oliver", "Lyssa Prine", "Yalonda Lisa Reeves", "C. Stuart Rome", "Lonnie Schaffer", "Chaz Smith", "Logan Douglas Smith", "Antoine Spillers", "Terri Stoor", "William S. Tribell", "M. Jearl Vinot", "Dawna Williams", "Cindy Williamson" ],
  "tags" : [ ]
}
