{
  "imdbId" : "3148266",
  "title" : "12 Monkeys - The Series",
  "releaseYear" : "2015",
  "duration" : "0:42",
  "rating" : "TV-14",
  "director" : "David Grossman",
  "imageUrl" : "3148266.jpg",
  "description" : "Follows the journey of a time traveler from the post-apocalyptic future who appears in present day on a mission to locate and eradicate the source of a deadly plague that will nearly destroy the human race.",
  "genres" : [ "Adventure", "Drama", "Mystery", "Sci-Fi" ],
  "cast" : [ "Demore Barnes", "Aaron Stanford", "Amanda Schull", "Barbara Sukowa", "Kirk Acevedo", "Noah Bean", "Emily Hampshire", "Andrew Gillies", "Tom Noonan", "Murray Furrow", "Alisen Down", "Bill Timoney", "Peter DaCunha", "Todd Stashwick", "Romina D'Ugo", "Scottie Thompson", "Ramon De Ocampo", "Amy Sloan", "Jee-Yun Lee", "Benjamin Meranda", "Jordan Claire Robbins", "Mitchell Verigin", "Ari Millen", "Xander Berkeley", "Zeljko Ivanek", "Adam Bogen", "Andreas Apergis", "Rothaford Gray", "Bryan Edwards", "Stephen McHattie", "Lyriq Bent", "Joshua Close", "Mark Margolis", "Patrick Garrow", "Alex Hatz", "Sam Kalilieh", "Peter Outerbridge", "Robert Wisdom", "Denis Akiyama", "Jeff Clarke", "Conrad Coates", "Calvin Desautels", "Philip Yang", "Michael Boisvert", "Mark Boyd", "Stefen Hayes", "Daniel Park", "James Pettitt", "ShaTyrah Dexter", "Lisa Messinger", "Joanne Reece", "Miguel Anthony", "Christine Aziz", "Susanna Fournier", "Jack Fulton", "Diane Johnstone", "Ramona Milano", "Harry Wetzel", "Eric Craig", "Julie Sifuentes Etheridge", "Bruce Hunter", "Dwight Ireland", "Billy MacLellan", "Michael Orr", "Nataliya Rodina", "Richard Waugh", "Glenn Bang", "Aura Carcueva", "Ingrid Gaynor", "Alex Loubert", "Lorena Mackenzie", "Sergey Shpakovsky", "Dan Warry-Smith", "Christian Bako", "Howard J. Davis", "Dan Fox", "Vlado Jovanovski", "Steve Park", "Patrick Romango", "Alex Spencer", "Kaleb Alexander", "Gary Augustynek", "Brad Austin", "Justine Campbell", "Dorly Jean-Louis", "Robin Kasyanov", "Brett Reason", "Adrian Rebucas", "Brianna Andrade-Gomes", "Sean Arbuckle", "Nicholas Hamzea", "Jung-Yul Kim", "Gjokica Trevski", "Minh Le", "Gjorgh Nestorovvski", "Katherine East", "Dejan Lilic", "Matt Smith", "Boyd Banks", "Thomas Saunders", "Nesrin Tair", "Paul Kingston", "Michael Brown", "Carlyn Burchell", "Craig Burnatowski", "Caleb Cosman", "David Dantes", "James Fanizza", "Justin Goodhand", "Eve Harlow", "Glenda MacInnis", "Xavier Schoppel", "Tiffany Shepis", "Adrian Spencer", "Shant Srabian", "Egidio Tari", "Robert Forte Shannon III", "James Lafazanos", "Sareeya McNally", "Brian R. Moore", "Caroline Rankin", "Nicholas Ritz", "Ricky Wayne", "Devlin Anderson", "Raffi Atamian", "Jennifer De Lucia", "Courtney Deelen", "Daniella Forget", "Shane Jarvis", "Tina Jung", "Fabio Lusvarghi", "Al McFoster", "Rose Anne Nepa", "Jared Michael Scott", "George Seder", "Troy Storm", "Brendt Thomas Diabo", "Scott Konkel" ],
  "tags" : [ "TV", "Time Travel" ]
}
