{
  "imdbId" : "9376612",
  "title" : "Shang-Chi and the Legend of the Ten Rings",
  "releaseYear" : "2021",
  "duration" : "2:12",
  "rating" : "PG-13",
  "director" : "Destin Daniel Cretton",
  "imageUrl" : "9376612.jpg",
  "description" : "Shang-Chi, the master of weaponry-based Kung Fu, is forced to confront his past after being drawn into the Ten Rings organization.",
  "genres" : [ "Action", "Adventure", "Fantasy" ],
  "cast" : [ "Simu Liu", "Tony Chiu-Wai Leung", "Awkwafina", "Ben Kingsley", "Meng'er Zhang", "Fala Chen", "Michelle Yeoh", "Wah Yuen", "Florian Munteanu", "Andy Le", "Paul W. He", "Jayden Zhang", "Elodie Fong", "Arnold Sun", "Stephanie Hsu", "Kunal Dudheker", "Tsai Chin", "Jodi Long", "Dallas Liu", "Ronny Chieng", "Daniel Liu", "Stella Ye", "Fernando Chien", "Michael-Anthony Taylor", "Zach Cherry", "Raymond Ma", "Thau Shen Lim", "Kar-Yung Lau", "Johnny Carr", "Harmonie He", "Lydia Sarks", "John Harding", "Lynette Curran", "Benjamin Wang", "Benedict Wong", "Jade Xu", "Shelley Xu", "Alistair Bates", "Dee Bradley Baker", "Kelli Bailey", "Alfred K. Chow", "Shaun Robert Foley", "Hannah Kim", "Brie Larson", "Christine Lee", "Mahal Montoya", "Christian Harris Neeman", "Tim Roth", "Mark Ruffalo", "Andy Thai", "Bingchen Ye" ],
  "tags" : [ "Marvel" ]
}
